{"GAME_ID":{"0":"0021900900","1":"0021900900","2":"0021900900","3":"0021900900","4":"0021900900","5":"0021900900","6":"0021900900","7":"0021900900","8":"0021900900","9":"0021900900","10":"0021900900","11":"0021900900","12":"0021900900","13":"0021900900","14":"0021900900","15":"0021900900","16":"0021900900","17":"0021900900","18":"0021900900"},"TEAM_ID":{"0":1610612747,"1":1610612747,"2":1610612747,"3":1610612747,"4":1610612747,"5":1610612747,"6":1610612747,"7":1610612747,"8":1610612747,"9":1610612747,"10":1610612740,"11":1610612740,"12":1610612740,"13":1610612740,"14":1610612740,"15":1610612740,"16":1610612740,"17":1610612740,"18":1610612740},"TEAM_ABBREVIATION":{"0":"LAL","1":"LAL","2":"LAL","3":"LAL","4":"LAL","5":"LAL","6":"LAL","7":"LAL","8":"LAL","9":"LAL","10":"NOP","11":"NOP","12":"NOP","13":"NOP","14":"NOP","15":"NOP","16":"NOP","17":"NOP","18":"NOP"},"TEAM_CITY":{"0":"Los Angeles","1":"Los Angeles","2":"Los Angeles","3":"Los Angeles","4":"Los Angeles","5":"Los Angeles","6":"Los Angeles","7":"Los Angeles","8":"Los Angeles","9":"Los Angeles","10":"New Orleans","11":"New Orleans","12":"New Orleans","13":"New Orleans","14":"New Orleans","15":"New Orleans","16":"New Orleans","17":"New Orleans","18":"New Orleans"},"TEAM_NICKNAME":{"0":"Lakers","1":"Lakers","2":"Lakers","3":"Lakers","4":"Lakers","5":"Lakers","6":"Lakers","7":"Lakers","8":"Lakers","9":"Lakers","10":"Pelicans","11":"Pelicans","12":"Pelicans","13":"Pelicans","14":"Pelicans","15":"Pelicans","16":"Pelicans","17":"Pelicans","18":"Pelicans"},"PLAYER_ID":{"0":2544,"1":1628398,"2":201580,"3":201980,"4":202340,"5":203484,"6":2730,"7":202693,"8":200765,"9":1626188,"10":1627742,"11":1629627,"12":202324,"13":201950,"14":1628366,"15":1628404,"16":1629740,"17":202734,"18":1628402},"PLAYER_NAME":{"0":"LeBron James","1":"Kyle Kuzma","2":"JaVale McGee","3":"Danny Green","4":"Avery Bradley","5":"Kentavious Caldwell-Pope","6":"Dwight Howard","7":"Markieff Morris","8":"Rajon Rondo","9":"Quinn Cook","10":"Brandon Ingram","11":"Zion Williamson","12":"Derrick Favors","13":"Jrue Holiday","14":"Lonzo Ball","15":"Josh Hart","16":"Nicolo Melli","17":"E'Twaun Moore","18":"Frank Jackson"},"START_POSITION":{"0":"F","1":"F","2":"C","3":"G","4":"G","5":"","6":"","7":"","8":"","9":"","10":"F","11":"F","12":"C","13":"G","14":"G","15":"","16":"","17":"","18":""},"COMMENT":{"0":"","1":"","2":"","3":"","4":"","5":"","6":"","7":"","8":"","9":"","10":"","11":"","12":"","13":"","14":"","15":"","16":"","17":"","18":""},"MATCHUP_MIN":{"0":"12:58","1":"12:31","2":"8:24","3":"7:47","4":"9:27","5":"11:02","6":"7:49","7":"5:14","8":"5:33","9":"4:11","10":"13:13","11":"11:19","12":"9:04","13":"13:07","14":"12:49","15":"8:20","16":"7:45","17":"6:27","18":"2:00"},"PARTIAL_POSS":{"0":51.39,"1":51.81,"2":34.89,"3":34.34,"4":41.0,"5":46.52,"6":31.62,"7":24.52,"8":23.58,"9":17.46,"10":55.23,"11":45.49,"12":38.39,"13":53.97,"14":50.71,"15":32.57,"16":29.9,"17":25.21,"18":9.99},"SWITCHES_ON":{"0":0,"1":0,"2":0,"3":0,"4":0,"5":0,"6":0,"7":0,"8":0,"9":0,"10":0,"11":0,"12":0,"13":0,"14":0,"15":0,"16":0,"17":0,"18":0},"PLAYER_PTS":{"0":7,"1":28,"2":9,"3":17,"4":9,"5":2,"6":7,"7":14,"8":7,"9":7,"10":14,"11":19,"12":16,"13":21,"14":12,"15":24,"16":8,"17":6,"18":2},"DREB":{"0":12,"1":3,"2":2,"3":3,"4":1,"5":0,"6":4,"7":4,"8":1,"9":0,"10":4,"11":5,"12":5,"13":4,"14":9,"15":4,"16":2,"17":3,"18":1},"MATCHUP_AST":{"0":3,"1":1,"2":0,"3":3,"4":1,"5":2,"6":1,"7":2,"8":1,"9":1,"10":2,"11":2,"12":2,"13":4,"14":3,"15":2,"16":1,"17":1,"18":0},"MATCHUP_TOV":{"0":4,"1":2,"2":3,"3":1,"4":2,"5":2,"6":1,"7":2,"8":0,"9":0,"10":2,"11":2,"12":2,"13":1,"14":1,"15":0,"16":1,"17":1,"18":0},"STL":{"0":2,"1":1,"2":0,"3":1,"4":1,"5":3,"6":0,"7":1,"8":0,"9":0,"10":1,"11":0,"12":1,"13":1,"14":3,"15":0,"16":1,"17":0,"18":0},"BLK":{"0":0,"1":0,"2":6,"3":0,"4":1,"5":1,"6":1,"7":0,"8":0,"9":0,"10":0,"11":0,"12":1,"13":0,"14":1,"15":0,"16":1,"17":0,"18":0},"MATCHUP_FGM":{"0":3,"1":11,"2":3,"3":7,"4":4,"5":0,"6":2,"7":4,"8":3,"9":2,"10":5,"11":8,"12":6,"13":8,"14":5,"15":10,"16":4,"17":3,"18":1},"MATCHUP_FGA":{"0":8,"1":19,"2":12,"3":18,"4":9,"5":2,"6":10,"7":7,"8":5,"9":4,"10":10,"11":15,"12":16,"13":15,"14":8,"15":18,"16":6,"17":5,"18":2},"MATCHUP_FG_PCT":{"0":0.375,"1":0.579,"2":0.25,"3":0.389,"4":0.444,"5":0.0,"6":0.2,"7":0.571,"8":0.6,"9":0.5,"10":0.5,"11":0.533,"12":0.375,"13":0.533,"14":0.625,"15":0.556,"16":0.667,"17":0.6,"18":0.5},"MATCHUP_FG3M":{"0":0,"1":1,"2":0,"3":2,"4":1,"5":0,"6":0,"7":0,"8":1,"9":0,"10":2,"11":3,"12":2,"13":1,"14":2,"15":3,"16":0,"17":0,"18":0},"MATCHUP_FG3A":{"0":4,"1":4,"2":0,"3":6,"4":3,"5":1,"6":4,"7":3,"8":3,"9":2,"10":3,"11":7,"12":5,"13":5,"14":3,"15":6,"16":1,"17":2,"18":1},"MATCHUP_FG3_PCT":{"0":0.0,"1":0.25,"2":0.0,"3":0.333,"4":0.333,"5":0.0,"6":0.0,"7":0.0,"8":0.333,"9":0.0,"10":0.667,"11":0.429,"12":0.4,"13":0.2,"14":0.667,"15":0.5,"16":0.0,"17":0.0,"18":0.0}}