{"teams": {"home": "BOS", "away": "POR"}, "stats": {"home": {"[202330, 202689, 1627759, 1628369, 1628464]": {"lineup": [202330, 202689, 1627759, 1628369, 1628464], "2ptm": 5, "3ptm": 4, "ftm": 5, "2pta": 8, "3pta": 7, "fta": 7, "poss": 20, "tov": 2, "ast": 6, "foul_s": 1, "foul_reg": 3, "d_reb": 8, "o_reb": 2, "min": 604, "subs": 2}, "[202330, 202689, 1627759, 202683, 1628464]": {"lineup": [202330, 202689, 1627759, 202683, 1628464], "2ptm": 0, "3ptm": 0, "ftm": 0, "2pta": 0, "3pta": 0, "fta": 0, "poss": 0, "tov": 0, "ast": 0, "foul_s": 0, "foul_reg": 0, "d_reb": 0, "o_reb": 0, "min": 0, "subs": 1}, "[202330, 203935, 1627759, 202683, 1628464]": {"lineup": [202330, 203935, 1627759, 202683, 1628464], "2ptm": 0, "3ptm": 0, "ftm": 0, "2pta": 0, "3pta": 0, "fta": 0, "poss": 0, "tov": 0, "ast": 0, "foul_s": 0, "foul_reg": 0, "d_reb": 0, "o_reb": 0, "min": 0, "subs": 1}, "[202330, 203935, 1627759, 202683, 202954]": {"lineup": [202330, 203935, 1627759, 202683, 202954], "2ptm": 2, "3ptm": 3, "ftm": 1, "2pta": 5, "3pta": 3, "fta": 2, "poss": 9, "tov": 0, "ast": 3, "foul_s": 1, "foul_reg": 0, "d_reb": 0, "o_reb": 4, "min": 208, "subs": 1}, "[202330, 203935, 1627759, 202683, 1629684]": {"lineup": [202330, 203935, 1627759, 202683, 1629684], "2ptm": 0, "3ptm": 0, "ftm": 0, "2pta": 0, "3pta": 0, "fta": 0, "poss": 0, "tov": 0, "ast": 0, "foul_s": 0, "foul_reg": 0, "d_reb": 0, "o_reb": 0, "min": 0, "subs": 1}, "[1628369, 203935, 1627759, 202683, 1629684]": {"lineup": [1628369, 203935, 1627759, 202683, 1629684], "2ptm": 1, "3ptm": 0, "ftm": 2, "2pta": 1, "3pta": 1, "fta": 4, "poss": 5, "tov": 1, "ast": 0, "foul_s": 0, "foul_reg": 0, "d_reb": 1, "o_reb": 3, "min": 96, "subs": 1}, "[1628369, 203935, 202689, 202683, 1629684]": {"lineup": [1628369, 203935, 202689, 202683, 1629684], "2ptm": 0, "3ptm": 1, "ftm": 0, "2pta": 0, "3pta": 1, "fta": 0, "poss": 1, "tov": 0, "ast": 0, "foul_s": 0, "foul_reg": 1, "d_reb": 0, "o_reb": 0, "min": 44, "subs": 1}, "[1628369, 203935, 202689, 1628464, 1629684]": {"lineup": [1628369, 203935, 202689, 1628464, 1629684], "2ptm": 0, "3ptm": 0, "ftm": 0, "2pta": 0, "3pta": 1, "fta": 0, "poss": 1, "tov": 0, "ast": 0, "foul_s": 0, "foul_reg": 0, "d_reb": 1, "o_reb": 0, "min": 25, "subs": 0}, "[202689, 203935, 1628369, 1628464, 1629684]": {"lineup": [202689, 203935, 1628369, 1628464, 1629684], "2ptm": 1, "3ptm": 0, "ftm": 0, "2pta": 2, "3pta": 1, "fta": 0, "poss": 3, "tov": 0, "ast": 1, "foul_s": 0, "foul_reg": 0, "d_reb": 1, "o_reb": 0, "min": 96, "subs": 1}, "[202689, 203935, 1628369, 1628464, 202683]": {"lineup": [202689, 203935, 1628369, 1628464, 202683], "2ptm": 0, "3ptm": 0, "ftm": 0, "2pta": 0, "3pta": 0, "fta": 0, "poss": 0, "tov": 0, "ast": 0, "foul_s": 0, "foul_reg": 0, "d_reb": 0, "o_reb": 0, "min": 0, "subs": 1}, "[202689, 203935, 1628369, 1628400, 202683]": {"lineup": [202689, 203935, 1628369, 1628400, 202683], "2ptm": 1, "3ptm": 2, "ftm": 0, "2pta": 4, "3pta": 2, "fta": 0, "poss": 6, "tov": 0, "ast": 1, "foul_s": 0, "foul_reg": 0, "d_reb": 3, "o_reb": 2, "min": 142, "subs": 1}, "[202689, 202330, 1628369, 1628400, 202683]": {"lineup": [202689, 202330, 1628369, 1628400, 202683], "2ptm": 2, "3ptm": 1, "ftm": 0, "2pta": 2, "3pta": 2, "fta": 0, "poss": 5, "tov": 1, "ast": 0, "foul_s": 0, "foul_reg": 2, "d_reb": 3, "o_reb": 0, "min": 138, "subs": 1}, "[202689, 202330, 1628464, 1628400, 202683]": {"lineup": [202689, 202330, 1628464, 1628400, 202683], "2ptm": 0, "3ptm": 0, "ftm": 0, "2pta": 0, "3pta": 0, "fta": 0, "poss": 0, "tov": 0, "ast": 0, "foul_s": 0, "foul_reg": 0, "d_reb": 0, "o_reb": 0, "min": 0, "subs": 1}, "[1627759, 202330, 1628464, 1628400, 202683]": {"lineup": [1627759, 202330, 1628464, 1628400, 202683], "2ptm": 0, "3ptm": 0, "ftm": 0, "2pta": 0, "3pta": 0, "fta": 0, "poss": 0, "tov": 0, "ast": 0, "foul_s": 0, "foul_reg": 0, "d_reb": 0, "o_reb": 0, "min": 0, "subs": 1}, "[1627759, 202330, 1628464, 1628400, 203935]": {"lineup": [1627759, 202330, 1628464, 1628400, 203935], "2ptm": 0, "3ptm": 1, "ftm": 1, "2pta": 1, "3pta": 2, "fta": 2, "poss": 5, "tov": 1, "ast": 1, "foul_s": 0, "foul_reg": 0, "d_reb": 1, "o_reb": 0, "min": 139, "subs": 1}, "[1627759, 202330, 1628464, 1628369, 203935]": {"lineup": [1627759, 202330, 1628464, 1628369, 203935], "2ptm": 1, "3ptm": 0, "ftm": 0, "2pta": 1, "3pta": 0, "fta": 0, "poss": 2, "tov": 1, "ast": 0, "foul_s": 1, "foul_reg": 1, "d_reb": 1, "o_reb": 0, "min": 71, "subs": 1}, "[1627759, 202330, 202683, 1628369, 203935]": {"lineup": [1627759, 202330, 202683, 1628369, 203935], "2ptm": 2, "3ptm": 0, "ftm": 3, "2pta": 4, "3pta": 0, "fta": 3, "poss": 5, "tov": 0, "ast": 1, "foul_s": 0, "foul_reg": 0, "d_reb": 1, "o_reb": 1, "min": 123, "subs": 1}, "[1627759, 202330, 1629684, 1628369, 203935]": {"lineup": [1627759, 202330, 1629684, 1628369, 203935], "2ptm": 0, "3ptm": 0, "ftm": 0, "2pta": 0, "3pta": 0, "fta": 0, "poss": 1, "tov": 1, "ast": 0, "foul_s": 0, "foul_reg": 1, "d_reb": 0, "o_reb": 0, "min": 11, "subs": 0}, "[202330, 203935, 1627759, 1628369, 1628464]": {"lineup": [202330, 203935, 1627759, 1628369, 1628464], "2ptm": 1, "3ptm": 2, "ftm": 0, "2pta": 2, "3pta": 2, "fta": 0, "poss": 4, "tov": 0, "ast": 3, "foul_s": 0, "foul_reg": 0, "d_reb": 0, "o_reb": 0, "min": 131, "subs": 1}, "[202330, 203935, 1627759, 1629684, 1628464]": {"lineup": [202330, 203935, 1627759, 1629684, 1628464], "2ptm": 0, "3ptm": 0, "ftm": 1, "2pta": 1, "3pta": 0, "fta": 1, "poss": 2, "tov": 1, "ast": 0, "foul_s": 2, "foul_reg": 0, "d_reb": 0, "o_reb": 1, "min": 60, "subs": 1}, "[202330, 203935, 202689, 1629684, 1628464]": {"lineup": [202330, 203935, 202689, 1629684, 1628464], "2ptm": 0, "3ptm": 0, "ftm": 0, "2pta": 0, "3pta": 1, "fta": 0, "poss": 1, "tov": 0, "ast": 0, "foul_s": 0, "foul_reg": 0, "d_reb": 0, "o_reb": 0, "min": 23, "subs": 1}, "[202330, 203935, 202689, 1629684, 202683]": {"lineup": [202330, 203935, 202689, 1629684, 202683], "2ptm": 1, "3ptm": 0, "ftm": 0, "2pta": 1, "3pta": 1, "fta": 0, "poss": 3, "tov": 1, "ast": 1, "foul_s": 0, "foul_reg": 0, "d_reb": 1, "o_reb": 0, "min": 77, "subs": 1}, "[202330, 203935, 202689, 1628369, 202683]": {"lineup": [202330, 203935, 202689, 1628369, 202683], "2ptm": 0, "3ptm": 0, "ftm": 0, "2pta": 0, "3pta": 0, "fta": 0, "poss": 0, "tov": 0, "ast": 0, "foul_s": 0, "foul_reg": 0, "d_reb": 0, "o_reb": 0, "min": 0, "subs": 1}, "[1628400, 203935, 202689, 1628369, 202683]": {"lineup": [1628400, 203935, 202689, 1628369, 202683], "2ptm": 0, "3ptm": 0, "ftm": 3, "2pta": 1, "3pta": 1, "fta": 4, "poss": 4, "tov": 0, "ast": 0, "foul_s": 0, "foul_reg": 1, "d_reb": 1, "o_reb": 1, "min": 87, "subs": 1}, "[1628400, 203935, 202689, 1628369, 1628464]": {"lineup": [1628400, 203935, 202689, 1628369, 1628464], "2ptm": 0, "3ptm": 0, "ftm": 0, "2pta": 1, "3pta": 0, "fta": 0, "poss": 2, "tov": 1, "ast": 0, "foul_s": 1, "foul_reg": 0, "d_reb": 1, "o_reb": 1, "min": 55, "subs": 1}, "[1627759, 203935, 202689, 1628369, 1628464]": {"lineup": [1627759, 203935, 202689, 1628369, 1628464], "2ptm": 1, "3ptm": 0, "ftm": 0, "2pta": 1, "3pta": 0, "fta": 0, "poss": 1, "tov": 0, "ast": 0, "foul_s": 0, "foul_reg": 0, "d_reb": 0, "o_reb": 0, "min": 30, "subs": 0}, "[202954, 203935, 1627759, 1628369, 1628464]": {"lineup": [202954, 203935, 1627759, 1628369, 1628464], "2ptm": 2, "3ptm": 1, "ftm": 0, "2pta": 4, "3pta": 2, "fta": 0, "poss": 7, "tov": 1, "ast": 3, "foul_s": 0, "foul_reg": 0, "d_reb": 0, "o_reb": 0, "min": 235, "subs": 1}, "[202954, 202330, 1627759, 1628369, 1628464]": {"lineup": [202954, 202330, 1627759, 1628369, 1628464], "2ptm": 0, "3ptm": 0, "ftm": 0, "2pta": 1, "3pta": 0, "fta": 0, "poss": 1, "tov": 0, "ast": 0, "foul_s": 0, "foul_reg": 0, "d_reb": 0, "o_reb": 0, "min": 22, "subs": 1}, "[202954, 202330, 1627759, 1628369, 202683]": {"lineup": [202954, 202330, 1627759, 1628369, 202683], "2ptm": 2, "3ptm": 1, "ftm": 1, "2pta": 4, "3pta": 1, "fta": 1, "poss": 5, "tov": 0, "ast": 2, "foul_s": 1, "foul_reg": 0, "d_reb": 2, "o_reb": 1, "min": 127, "subs": 1}, "[203935, 202330, 1627759, 1628369, 202683]": {"lineup": [203935, 202330, 1627759, 1628369, 202683], "2ptm": 0, "3ptm": 1, "ftm": 4, "2pta": 1, "3pta": 1, "fta": 4, "poss": 5, "tov": 1, "ast": 1, "foul_s": 0, "foul_reg": 1, "d_reb": 2, "o_reb": 0, "min": 153, "subs": 1}, "[203935, 202330, 1627759, 1628369, 1628464]": {"lineup": [203935, 202330, 1627759, 1628369, 1628464], "2ptm": 2, "3ptm": 1, "ftm": 5, "2pta": 2, "3pta": 1, "fta": 6, "poss": 8, "tov": 2, "ast": 1, "foul_s": 0, "foul_reg": 2, "d_reb": 2, "o_reb": 1, "min": 183, "subs": 0}}, "away": {"[2546, 203081, 203468, 203994, 1628380]": {"lineup": [2546, 203081, 203468, 203994, 1628380], "2ptm": 10, "3ptm": 2, "ftm": 2, "2pta": 14, "3pta": 4, "fta": 2, "poss": 19, "tov": 0, "ast": 9, "foul_s": 5, "foul_reg": 3, "d_reb": 6, "o_reb": 1, "min": 639, "subs": 2}, "[2546, 203081, 203468, 203994, 1626209]": {"lineup": [2546, 203081, 203468, 203994, 1626209], "2ptm": 2, "3ptm": 0, "ftm": 1, "2pta": 4, "3pta": 2, "fta": 1, "poss": 7, "tov": 0, "ast": 2, "foul_s": 0, "foul_reg": 0, "d_reb": 1, "o_reb": 1, "min": 163, "subs": 1}, "[2546, 203081, 203468, 202355, 1626209]": {"lineup": [2546, 203081, 203468, 202355, 1626209], "2ptm": 0, "3ptm": 0, "ftm": 1, "2pta": 0, "3pta": 0, "fta": 1, "poss": 0, "tov": 0, "ast": 0, "foul_s": 0, "foul_reg": 0, "d_reb": 0, "o_reb": 0, "min": 42, "subs": 1}, "[1629018, 203081, 203468, 202355, 1626209]": {"lineup": [1629018, 203081, 203468, 202355, 1626209], "2ptm": 0, "3ptm": 0, "ftm": 0, "2pta": 0, "3pta": 0, "fta": 0, "poss": 0, "tov": 0, "ast": 0, "foul_s": 0, "foul_reg": 0, "d_reb": 0, "o_reb": 0, "min": 0, "subs": 1}, "[1629018, 203081, 1628380, 202355, 1626209]": {"lineup": [1629018, 203081, 1628380, 202355, 1626209], "2ptm": 2, "3ptm": 1, "ftm": 0, "2pta": 2, "3pta": 3, "fta": 0, "poss": 5, "tov": 0, "ast": 2, "foul_s": 1, "foul_reg": 2, "d_reb": 1, "o_reb": 1, "min": 195, "subs": 1}, "[1629018, 203081, 2546, 202355, 1626209]": {"lineup": [1629018, 203081, 2546, 202355, 1626209], "2ptm": 1, "3ptm": 0, "ftm": 0, "2pta": 1, "3pta": 1, "fta": 0, "poss": 2, "tov": 0, "ast": 0, "foul_s": 0, "foul_reg": 0, "d_reb": 1, "o_reb": 1, "min": 44, "subs": 1}, "[1629018, 203081, 2546, 203468, 1626209]": {"lineup": [1629018, 203081, 2546, 203468, 1626209], "2ptm": 0, "3ptm": 0, "ftm": 0, "2pta": 0, "3pta": 1, "fta": 0, "poss": 1, "tov": 0, "ast": 0, "foul_s": 0, "foul_reg": 0, "d_reb": 2, "o_reb": 0, "min": 25, "subs": 0}, "[2546, 203468, 203994, 1626209, 1629018]": {"lineup": [2546, 203468, 203994, 1626209, 1629018], "2ptm": 0, "3ptm": 1, "ftm": 0, "2pta": 2, "3pta": 4, "fta": 0, "poss": 6, "tov": 0, "ast": 1, "foul_s": 0, "foul_reg": 0, "d_reb": 4, "o_reb": 1, "min": 238, "subs": 1}, "[2546, 203468, 203994, 203081, 1629018]": {"lineup": [2546, 203468, 203994, 203081, 1629018], "2ptm": 4, "3ptm": 3, "ftm": 4, "2pta": 6, "3pta": 7, "fta": 4, "poss": 15, "tov": 0, "ast": 4, "foul_s": 2, "foul_reg": 2, "d_reb": 5, "o_reb": 1, "min": 481, "subs": 1}, "[2546, 1626209, 203994, 203081, 1629018]": {"lineup": [2546, 1626209, 203994, 203081, 1629018], "2ptm": 0, "3ptm": 0, "ftm": 0, "2pta": 0, "3pta": 0, "fta": 0, "poss": 0, "tov": 0, "ast": 0, "foul_s": 0, "foul_reg": 0, "d_reb": 0, "o_reb": 0, "min": 1, "subs": 0}, "[1629018, 203081, 203468, 203994, 1628380]": {"lineup": [1629018, 203081, 203468, 203994, 1628380], "2ptm": 1, "3ptm": 0, "ftm": 3, "2pta": 1, "3pta": 1, "fta": 3, "poss": 4, "tov": 1, "ast": 1, "foul_s": 0, "foul_reg": 0, "d_reb": 2, "o_reb": 1, "min": 83, "subs": 1}, "[1629018, 203081, 203468, 202355, 1628380]": {"lineup": [1629018, 203081, 203468, 202355, 1628380], "2ptm": 1, "3ptm": 1, "ftm": 0, "2pta": 2, "3pta": 1, "fta": 0, "poss": 3, "tov": 0, "ast": 1, "foul_s": 0, "foul_reg": 1, "d_reb": 1, "o_reb": 0, "min": 77, "subs": 1}, "[1629018, 203081, 2546, 202355, 1628380]": {"lineup": [1629018, 203081, 2546, 202355, 1628380], "2ptm": 0, "3ptm": 2, "ftm": 3, "2pta": 1, "3pta": 4, "fta": 3, "poss": 6, "tov": 0, "ast": 1, "foul_s": 0, "foul_reg": 1, "d_reb": 2, "o_reb": 1, "min": 172, "subs": 0}, "[202355, 203081, 203468, 1628380, 1629018]": {"lineup": [202355, 203081, 203468, 1628380, 1629018], "2ptm": 2, "3ptm": 6, "ftm": 1, "2pta": 2, "3pta": 9, "fta": 2, "poss": 13, "tov": 1, "ast": 5, "foul_s": 1, "foul_reg": 1, "d_reb": 5, "o_reb": 2, "min": 401, "subs": 1}, "[203994, 203081, 203468, 1628380, 1629018]": {"lineup": [203994, 203081, 203468, 1628380, 1629018], "2ptm": 0, "3ptm": 0, "ftm": 0, "2pta": 2, "3pta": 0, "fta": 0, "poss": 2, "tov": 0, "ast": 0, "foul_s": 1, "foul_reg": 0, "d_reb": 1, "o_reb": 0, "min": 78, "subs": 1}, "[203994, 203081, 203468, 2546, 1629018]": {"lineup": [203994, 203081, 203468, 2546, 1629018], "2ptm": 3, "3ptm": 3, "ftm": 0, "2pta": 5, "3pta": 5, "fta": 0, "poss": 11, "tov": 1, "ast": 5, "foul_s": 1, "foul_reg": 3, "d_reb": 0, "o_reb": 2, "min": 241, "subs": 0}}}}