{"teams": {"home": "MEM", "away": "GSW"}, "stats": {"home": {"[202685, 203109, 1628415, 1628991, 1629630]": {"lineup": [202685, 203109, 1628415, 1628991, 1629630], "2ptm": 7, "3ptm": 2, "ftm": 1, "2pta": 15, "3pta": 8, "fta": 1, "poss": 26, "tov": 3, "ast": 6, "foul_s": 3, "foul_reg": 2, "d_reb": 9, "o_reb": 3, "min": 671, "subs": 2}, "[202685, 203109, 1628415, 1628991, 1626145]": {"lineup": [202685, 203109, 1628415, 1628991, 1626145], "2ptm": 0, "3ptm": 0, "ftm": 0, "2pta": 0, "3pta": 0, "fta": 0, "poss": 0, "tov": 0, "ast": 0, "foul_s": 0, "foul_reg": 0, "d_reb": 0, "o_reb": 0, "min": 0, "subs": 1}, "[1629634, 203109, 1628415, 1628991, 1626145]": {"lineup": [1629634, 203109, 1628415, 1628991, 1626145], "2ptm": 3, "3ptm": 2, "ftm": 0, "2pta": 5, "3pta": 3, "fta": 1, "poss": 8, "tov": 0, "ast": 2, "foul_s": 0, "foul_reg": 0, "d_reb": 4, "o_reb": 1, "min": 215, "subs": 2}, "[1629634, 203109, 203937, 1628991, 1626145]": {"lineup": [1629634, 203109, 203937, 1628991, 1626145], "2ptm": 0, "3ptm": 0, "ftm": 0, "2pta": 1, "3pta": 0, "fta": 0, "poss": 2, "tov": 1, "ast": 0, "foul_s": 0, "foul_reg": 1, "d_reb": 1, "o_reb": 0, "min": 35, "subs": 1}, "[1629634, 203109, 203937, 203524, 1626145]": {"lineup": [1629634, 203109, 203937, 203524, 1626145], "2ptm": 2, "3ptm": 0, "ftm": 0, "2pta": 4, "3pta": 0, "fta": 0, "poss": 4, "tov": 0, "ast": 2, "foul_s": 0, "foul_reg": 0, "d_reb": 1, "o_reb": 1, "min": 76, "subs": 1}, "[1629634, 1629741, 203937, 203524, 1626145]": {"lineup": [1629634, 1629741, 203937, 203524, 1626145], "2ptm": 3, "3ptm": 0, "ftm": 2, "2pta": 5, "3pta": 1, "fta": 2, "poss": 7, "tov": 0, "ast": 3, "foul_s": 1, "foul_reg": 0, "d_reb": 4, "o_reb": 0, "min": 174, "subs": 1}, "[1629634, 1629741, 203937, 203524, 1629630]": {"lineup": [1629634, 1629741, 203937, 203524, 1629630], "2ptm": 1, "3ptm": 0, "ftm": 1, "2pta": 1, "3pta": 0, "fta": 1, "poss": 2, "tov": 1, "ast": 1, "foul_s": 0, "foul_reg": 0, "d_reb": 0, "o_reb": 0, "min": 72, "subs": 0}, "[202685, 203524, 203937, 1628415, 1629630]": {"lineup": [202685, 203524, 203937, 1628415, 1629630], "2ptm": 1, "3ptm": 0, "ftm": 0, "2pta": 4, "3pta": 1, "fta": 0, "poss": 8, "tov": 3, "ast": 1, "foul_s": 0, "foul_reg": 2, "d_reb": 1, "o_reb": 2, "min": 212, "subs": 1}, "[202685, 203524, 1628991, 1628415, 1629630]": {"lineup": [202685, 203524, 1628991, 1628415, 1629630], "2ptm": 0, "3ptm": 0, "ftm": 0, "2pta": 0, "3pta": 0, "fta": 0, "poss": 0, "tov": 0, "ast": 0, "foul_s": 0, "foul_reg": 0, "d_reb": 0, "o_reb": 0, "min": 0, "subs": 1}, "[203109, 203524, 1628991, 1628415, 1629630]": {"lineup": [203109, 203524, 1628991, 1628415, 1629630], "2ptm": 0, "3ptm": 0, "ftm": 0, "2pta": 1, "3pta": 0, "fta": 0, "poss": 1, "tov": 0, "ast": 0, "foul_s": 0, "foul_reg": 0, "d_reb": 1, "o_reb": 0, "min": 35, "subs": 1}, "[203109, 1629634, 1628991, 1628415, 1629630]": {"lineup": [203109, 1629634, 1628991, 1628415, 1629630], "2ptm": 0, "3ptm": 0, "ftm": 0, "2pta": 1, "3pta": 0, "fta": 0, "poss": 1, "tov": 0, "ast": 0, "foul_s": 1, "foul_reg": 0, "d_reb": 0, "o_reb": 0, "min": 20, "subs": 1}, "[203109, 1629634, 203998, 1628415, 1629630]": {"lineup": [203109, 1629634, 203998, 1628415, 1629630], "2ptm": 1, "3ptm": 0, "ftm": 0, "2pta": 2, "3pta": 1, "fta": 0, "poss": 4, "tov": 1, "ast": 0, "foul_s": 1, "foul_reg": 1, "d_reb": 1, "o_reb": 0, "min": 86, "subs": 1}, "[203109, 1629634, 203937, 1628415, 1629630]": {"lineup": [203109, 1629634, 203937, 1628415, 1629630], "2ptm": 0, "3ptm": 0, "ftm": 0, "2pta": 0, "3pta": 0, "fta": 0, "poss": 0, "tov": 0, "ast": 0, "foul_s": 0, "foul_reg": 0, "d_reb": 0, "o_reb": 0, "min": 0, "subs": 1}, "[203109, 1629634, 203937, 1628415, 1626145]": {"lineup": [203109, 1629634, 203937, 1628415, 1626145], "2ptm": 0, "3ptm": 0, "ftm": 0, "2pta": 3, "3pta": 1, "fta": 0, "poss": 4, "tov": 0, "ast": 0, "foul_s": 0, "foul_reg": 0, "d_reb": 0, "o_reb": 1, "min": 113, "subs": 1}, "[203109, 1629634, 203937, 203524, 1626145]": {"lineup": [203109, 1629634, 203937, 203524, 1626145], "2ptm": 0, "3ptm": 0, "ftm": 0, "2pta": 0, "3pta": 0, "fta": 0, "poss": 0, "tov": 0, "ast": 0, "foul_s": 0, "foul_reg": 0, "d_reb": 0, "o_reb": 0, "min": 0, "subs": 1}, "[203109, 1629634, 203937, 203524, 1629630]": {"lineup": [203109, 1629634, 203937, 203524, 1629630], "2ptm": 0, "3ptm": 0, "ftm": 0, "2pta": 2, "3pta": 0, "fta": 0, "poss": 2, "tov": 0, "ast": 0, "foul_s": 0, "foul_reg": 0, "d_reb": 0, "o_reb": 0, "min": 41, "subs": 1}, "[203109, 202685, 203937, 203524, 1629630]": {"lineup": [203109, 202685, 203937, 203524, 1629630], "2ptm": 1, "3ptm": 2, "ftm": 4, "2pta": 2, "3pta": 2, "fta": 6, "poss": 7, "tov": 0, "ast": 3, "foul_s": 0, "foul_reg": 0, "d_reb": 2, "o_reb": 2, "min": 213, "subs": 0}, "[1629634, 203109, 1628415, 1628991, 1629630]": {"lineup": [1629634, 203109, 1628415, 1628991, 1629630], "2ptm": 0, "3ptm": 0, "ftm": 1, "2pta": 0, "3pta": 0, "fta": 1, "poss": 1, "tov": 0, "ast": 0, "foul_s": 1, "foul_reg": 0, "d_reb": 0, "o_reb": 0, "min": 28, "subs": 1}, "[1629634, 203109, 1628415, 203937, 1626145]": {"lineup": [1629634, 203109, 1628415, 203937, 1626145], "2ptm": 0, "3ptm": 0, "ftm": 0, "2pta": 0, "3pta": 0, "fta": 0, "poss": 0, "tov": 0, "ast": 0, "foul_s": 0, "foul_reg": 0, "d_reb": 0, "o_reb": 0, "min": 0, "subs": 1}, "[1629634, 203524, 1628415, 203937, 1626145]": {"lineup": [1629634, 203524, 1628415, 203937, 1626145], "2ptm": 2, "3ptm": 0, "ftm": 1, "2pta": 4, "3pta": 0, "fta": 2, "poss": 5, "tov": 1, "ast": 1, "foul_s": 1, "foul_reg": 1, "d_reb": 3, "o_reb": 0, "min": 120, "subs": 1}, "[1629634, 203524, 1628415, 203937, 1629630]": {"lineup": [1629634, 203524, 1628415, 203937, 1629630], "2ptm": 1, "3ptm": 0, "ftm": 0, "2pta": 1, "3pta": 1, "fta": 0, "poss": 2, "tov": 0, "ast": 1, "foul_s": 0, "foul_reg": 0, "d_reb": 0, "o_reb": 0, "min": 49, "subs": 0}, "[203524, 203937, 1628991, 1629001, 1629630]": {"lineup": [203524, 203937, 1628991, 1629001, 1629630], "2ptm": 0, "3ptm": 0, "ftm": 0, "2pta": 1, "3pta": 0, "fta": 0, "poss": 2, "tov": 1, "ast": 0, "foul_s": 0, "foul_reg": 0, "d_reb": 0, "o_reb": 0, "min": 50, "subs": 1}, "[203524, 203937, 202685, 1629001, 1629630]": {"lineup": [203524, 203937, 202685, 1629001, 1629630], "2ptm": 1, "3ptm": 0, "ftm": 1, "2pta": 2, "3pta": 0, "fta": 1, "poss": 2, "tov": 0, "ast": 1, "foul_s": 1, "foul_reg": 0, "d_reb": 1, "o_reb": 0, "min": 92, "subs": 1}, "[203524, 203109, 202685, 1629001, 1629630]": {"lineup": [203524, 203109, 202685, 1629001, 1629630], "2ptm": 0, "3ptm": 0, "ftm": 0, "2pta": 0, "3pta": 1, "fta": 0, "poss": 2, "tov": 1, "ast": 0, "foul_s": 1, "foul_reg": 0, "d_reb": 0, "o_reb": 0, "min": 64, "subs": 1}, "[203524, 203109, 202685, 1629634, 1629630]": {"lineup": [203524, 203109, 202685, 1629634, 1629630], "2ptm": 0, "3ptm": 0, "ftm": 0, "2pta": 0, "3pta": 0, "fta": 0, "poss": 0, "tov": 0, "ast": 0, "foul_s": 0, "foul_reg": 0, "d_reb": 0, "o_reb": 0, "min": 0, "subs": 1}, "[1628415, 203109, 202685, 1629634, 1629630]": {"lineup": [1628415, 203109, 202685, 1629634, 1629630], "2ptm": 4, "3ptm": 3, "ftm": 0, "2pta": 5, "3pta": 4, "fta": 0, "poss": 10, "tov": 1, "ast": 5, "foul_s": 1, "foul_reg": 0, "d_reb": 4, "o_reb": 0, "min": 337, "subs": 2}, "[1628415, 203109, 1628991, 1629634, 1629630]": {"lineup": [1628415, 203109, 1628991, 1629634, 1629630], "2ptm": 0, "3ptm": 0, "ftm": 0, "2pta": 1, "3pta": 1, "fta": 0, "poss": 2, "tov": 0, "ast": 0, "foul_s": 0, "foul_reg": 1, "d_reb": 0, "o_reb": 0, "min": 54, "subs": 1}, "[1629741, 203109, 202685, 1629634, 1629630]": {"lineup": [1629741, 203109, 202685, 1629634, 1629630], "2ptm": 0, "3ptm": 0, "ftm": 0, "2pta": 0, "3pta": 0, "fta": 0, "poss": 0, "tov": 0, "ast": 0, "foul_s": 0, "foul_reg": 0, "d_reb": 0, "o_reb": 0, "min": 0, "subs": 1}, "[1629741, 1629001, 202685, 1629634, 1629630]": {"lineup": [1629741, 1629001, 202685, 1629634, 1629630], "2ptm": 0, "3ptm": 0, "ftm": 1, "2pta": 0, "3pta": 0, "fta": 1, "poss": 1, "tov": 0, "ast": 0, "foul_s": 0, "foul_reg": 0, "d_reb": 0, "o_reb": 0, "min": 0, "subs": 1}, "[1629741, 1629001, 203524, 1629634, 1629630]": {"lineup": [1629741, 1629001, 203524, 1629634, 1629630], "2ptm": 0, "3ptm": 0, "ftm": 1, "2pta": 1, "3pta": 1, "fta": 1, "poss": 2, "tov": 0, "ast": 0, "foul_s": 0, "foul_reg": 1, "d_reb": 0, "o_reb": 0, "min": 51, "subs": 1}, "[1629741, 1629001, 203524, 1629634, 1626145]": {"lineup": [1629741, 1629001, 203524, 1629634, 1626145], "2ptm": 0, "3ptm": 0, "ftm": 1, "2pta": 2, "3pta": 0, "fta": 2, "poss": 4, "tov": 1, "ast": 0, "foul_s": 0, "foul_reg": 0, "d_reb": 0, "o_reb": 3, "min": 72, "subs": 0}}, "away": {"[202692, 203110, 203922, 1626161, 1629672]": {"lineup": [202692, 203110, 203922, 1626161, 1629672], "2ptm": 10, "3ptm": 1, "ftm": 6, "2pta": 16, "3pta": 6, "fta": 6, "poss": 25, "tov": 1, "ast": 11, "foul_s": 2, "foul_reg": 3, "d_reb": 12, "o_reb": 1, "min": 768, "subs": 2}, "[202692, 203110, 203922, 1629065, 1629672]": {"lineup": [202692, 203110, 203922, 1629065, 1629672], "2ptm": 0, "3ptm": 0, "ftm": 0, "2pta": 0, "3pta": 0, "fta": 0, "poss": 0, "tov": 0, "ast": 0, "foul_s": 0, "foul_reg": 0, "d_reb": 0, "o_reb": 0, "min": 0, "subs": 1}, "[1627737, 203110, 203922, 1629065, 1629672]": {"lineup": [1627737, 203110, 203922, 1629065, 1629672], "2ptm": 0, "3ptm": 0, "ftm": 0, "2pta": 0, "3pta": 1, "fta": 0, "poss": 2, "tov": 1, "ast": 0, "foul_s": 0, "foul_reg": 0, "d_reb": 0, "o_reb": 0, "min": 30, "subs": 1}, "[1627737, 1629673, 203922, 1629065, 1629672]": {"lineup": [1627737, 1629673, 203922, 1629065, 1629672], "2ptm": 1, "3ptm": 0, "ftm": 0, "2pta": 1, "3pta": 0, "fta": 0, "poss": 1, "tov": 0, "ast": 1, "foul_s": 1, "foul_reg": 0, "d_reb": 1, "o_reb": 0, "min": 46, "subs": 1}, "[1627737, 1629673, 203922, 1629065, 1629016]": {"lineup": [1627737, 1629673, 203922, 1629065, 1629016], "2ptm": 1, "3ptm": 0, "ftm": 0, "2pta": 1, "3pta": 1, "fta": 0, "poss": 2, "tov": 0, "ast": 1, "foul_s": 0, "foul_reg": 0, "d_reb": 2, "o_reb": 0, "min": 73, "subs": 1}, "[1627737, 1629673, 202692, 1629065, 1629016]": {"lineup": [1627737, 1629673, 202692, 1629065, 1629016], "2ptm": 1, "3ptm": 1, "ftm": 1, "2pta": 3, "3pta": 5, "fta": 2, "poss": 10, "tov": 1, "ast": 1, "foul_s": 1, "foul_reg": 0, "d_reb": 1, "o_reb": 4, "min": 173, "subs": 0}, "[202692, 1627737, 1629016, 1629065, 1629673]": {"lineup": [202692, 1627737, 1629016, 1629065, 1629673], "2ptm": 0, "3ptm": 2, "ftm": 0, "2pta": 0, "3pta": 2, "fta": 0, "poss": 3, "tov": 1, "ast": 2, "foul_s": 0, "foul_reg": 0, "d_reb": 2, "o_reb": 0, "min": 119, "subs": 1}, "[203110, 1627737, 1629016, 1629065, 1629673]": {"lineup": [203110, 1627737, 1629016, 1629065, 1629673], "2ptm": 2, "3ptm": 0, "ftm": 0, "2pta": 5, "3pta": 1, "fta": 0, "poss": 6, "tov": 0, "ast": 2, "foul_s": 0, "foul_reg": 1, "d_reb": 2, "o_reb": 1, "min": 128, "subs": 1}, "[203110, 1627737, 1629016, 203922, 1629673]": {"lineup": [203110, 1627737, 1629016, 203922, 1629673], "2ptm": 0, "3ptm": 0, "ftm": 2, "2pta": 0, "3pta": 1, "fta": 2, "poss": 3, "tov": 1, "ast": 0, "foul_s": 0, "foul_reg": 0, "d_reb": 2, "o_reb": 1, "min": 45, "subs": 1}, "[203110, 1627737, 1626161, 203922, 1629673]": {"lineup": [203110, 1627737, 1626161, 203922, 1629673], "2ptm": 0, "3ptm": 0, "ftm": 0, "2pta": 0, "3pta": 0, "fta": 0, "poss": 0, "tov": 0, "ast": 0, "foul_s": 0, "foul_reg": 0, "d_reb": 0, "o_reb": 0, "min": 0, "subs": 1}, "[203110, 1629672, 1626161, 203922, 1629673]": {"lineup": [203110, 1629672, 1626161, 203922, 1629673], "2ptm": 0, "3ptm": 0, "ftm": 1, "2pta": 1, "3pta": 1, "fta": 1, "poss": 3, "tov": 0, "ast": 0, "foul_s": 0, "foul_reg": 0, "d_reb": 1, "o_reb": 1, "min": 48, "subs": 1}, "[203110, 1629672, 1626161, 203922, 202692]": {"lineup": [203110, 1629672, 1626161, 203922, 202692], "2ptm": 6, "3ptm": 0, "ftm": 1, "2pta": 7, "3pta": 0, "fta": 1, "poss": 7, "tov": 0, "ast": 5, "foul_s": 0, "foul_reg": 4, "d_reb": 6, "o_reb": 0, "min": 222, "subs": 1}, "[203110, 1629065, 1626161, 203922, 202692]": {"lineup": [203110, 1629065, 1626161, 203922, 202692], "2ptm": 3, "3ptm": 0, "ftm": 0, "2pta": 3, "3pta": 0, "fta": 0, "poss": 3, "tov": 0, "ast": 0, "foul_s": 1, "foul_reg": 1, "d_reb": 1, "o_reb": 0, "min": 122, "subs": 1}, "[203110, 1629065, 1626161, 1629016, 202692]": {"lineup": [203110, 1629065, 1626161, 1629016, 202692], "2ptm": 0, "3ptm": 0, "ftm": 0, "2pta": 0, "3pta": 0, "fta": 0, "poss": 0, "tov": 0, "ast": 0, "foul_s": 0, "foul_reg": 0, "d_reb": 0, "o_reb": 0, "min": 0, "subs": 1}, "[1629673, 1629065, 1626161, 1629016, 202692]": {"lineup": [1629673, 1629065, 1626161, 1629016, 202692], "2ptm": 0, "3ptm": 0, "ftm": 0, "2pta": 1, "3pta": 1, "fta": 0, "poss": 2, "tov": 0, "ast": 0, "foul_s": 0, "foul_reg": 0, "d_reb": 0, "o_reb": 1, "min": 36, "subs": 0}, "[202692, 203110, 1629673, 1626161, 1629672]": {"lineup": [202692, 203110, 1629673, 1626161, 1629672], "2ptm": 0, "3ptm": 0, "ftm": 0, "2pta": 2, "3pta": 0, "fta": 0, "poss": 2, "tov": 0, "ast": 0, "foul_s": 0, "foul_reg": 0, "d_reb": 1, "o_reb": 0, "min": 56, "subs": 1}, "[202692, 203110, 1629673, 1627737, 1629672]": {"lineup": [202692, 203110, 1629673, 1627737, 1629672], "2ptm": 1, "3ptm": 0, "ftm": 0, "2pta": 1, "3pta": 0, "fta": 0, "poss": 1, "tov": 0, "ast": 1, "foul_s": 0, "foul_reg": 1, "d_reb": 0, "o_reb": 0, "min": 22, "subs": 1}, "[202692, 203110, 1629673, 1627737, 1629016]": {"lineup": [202692, 203110, 1629673, 1627737, 1629016], "2ptm": 0, "3ptm": 0, "ftm": 0, "2pta": 0, "3pta": 0, "fta": 0, "poss": 0, "tov": 0, "ast": 0, "foul_s": 0, "foul_reg": 0, "d_reb": 0, "o_reb": 0, "min": 0, "subs": 1}, "[1629065, 203110, 1629673, 1627737, 1629016]": {"lineup": [1629065, 203110, 1629673, 1627737, 1629016], "2ptm": 1, "3ptm": 1, "ftm": 0, "2pta": 2, "3pta": 1, "fta": 0, "poss": 3, "tov": 0, "ast": 2, "foul_s": 0, "foul_reg": 0, "d_reb": 2, "o_reb": 0, "min": 103, "subs": 1}, "[1629065, 203922, 1629673, 1627737, 1629016]": {"lineup": [1629065, 203922, 1629673, 1627737, 1629016], "2ptm": 0, "3ptm": 0, "ftm": 0, "2pta": 1, "3pta": 0, "fta": 0, "poss": 2, "tov": 1, "ast": 0, "foul_s": 2, "foul_reg": 0, "d_reb": 1, "o_reb": 0, "min": 71, "subs": 1}, "[1629065, 203922, 202692, 1627737, 1629016]": {"lineup": [1629065, 203922, 202692, 1627737, 1629016], "2ptm": 1, "3ptm": 0, "ftm": 2, "2pta": 3, "3pta": 1, "fta": 2, "poss": 5, "tov": 0, "ast": 0, "foul_s": 0, "foul_reg": 0, "d_reb": 3, "o_reb": 2, "min": 98, "subs": 0}, "[202692, 203922, 1627737, 1629016, 1629065]": {"lineup": [202692, 203922, 1627737, 1629016, 1629065], "2ptm": 1, "3ptm": 1, "ftm": 0, "2pta": 1, "3pta": 2, "fta": 0, "poss": 4, "tov": 1, "ast": 2, "foul_s": 1, "foul_reg": 1, "d_reb": 2, "o_reb": 1, "min": 114, "subs": 1}, "[203110, 203922, 1627737, 1629016, 1629065]": {"lineup": [203110, 203922, 1627737, 1629016, 1629065], "2ptm": 1, "3ptm": 0, "ftm": 0, "2pta": 2, "3pta": 0, "fta": 0, "poss": 2, "tov": 0, "ast": 0, "foul_s": 0, "foul_reg": 0, "d_reb": 1, "o_reb": 1, "min": 27, "subs": 1}, "[203110, 1629672, 1627737, 1629016, 1629065]": {"lineup": [203110, 1629672, 1627737, 1629016, 1629065], "2ptm": 2, "3ptm": 0, "ftm": 1, "2pta": 3, "3pta": 0, "fta": 3, "poss": 5, "tov": 1, "ast": 1, "foul_s": 0, "foul_reg": 1, "d_reb": 2, "o_reb": 2, "min": 123, "subs": 1}, "[203110, 202692, 1627737, 1629016, 1629065]": {"lineup": [203110, 202692, 1627737, 1629016, 1629065], "2ptm": 1, "3ptm": 0, "ftm": 0, "2pta": 1, "3pta": 0, "fta": 0, "poss": 2, "tov": 1, "ast": 0, "foul_s": 0, "foul_reg": 0, "d_reb": 1, "o_reb": 0, "min": 55, "subs": 1}, "[203110, 202692, 1626161, 1629016, 1629065]": {"lineup": [203110, 202692, 1626161, 1629016, 1629065], "2ptm": 0, "3ptm": 0, "ftm": 0, "2pta": 0, "3pta": 1, "fta": 0, "poss": 1, "tov": 0, "ast": 0, "foul_s": 0, "foul_reg": 0, "d_reb": 1, "o_reb": 0, "min": 43, "subs": 1}, "[203110, 202692, 1626161, 1629016, 203922]": {"lineup": [203110, 202692, 1626161, 1629016, 203922], "2ptm": 1, "3ptm": 1, "ftm": 0, "2pta": 2, "3pta": 1, "fta": 0, "poss": 3, "tov": 0, "ast": 2, "foul_s": 0, "foul_reg": 0, "d_reb": 0, "o_reb": 0, "min": 88, "subs": 1}, "[203110, 202692, 1626161, 1629672, 203922]": {"lineup": [203110, 202692, 1626161, 1629672, 203922], "2ptm": 1, "3ptm": 0, "ftm": 2, "2pta": 2, "3pta": 1, "fta": 2, "poss": 4, "tov": 0, "ast": 0, "foul_s": 1, "foul_reg": 0, "d_reb": 1, "o_reb": 0, "min": 147, "subs": 1}, "[203110, 202692, 1626161, 1629065, 203922]": {"lineup": [203110, 202692, 1626161, 1629065, 203922], "2ptm": 0, "3ptm": 1, "ftm": 1, "2pta": 0, "3pta": 1, "fta": 1, "poss": 2, "tov": 0, "ast": 1, "foul_s": 0, "foul_reg": 0, "d_reb": 2, "o_reb": 0, "min": 51, "subs": 1}, "[203110, 202692, 1629016, 1629065, 203922]": {"lineup": [203110, 202692, 1629016, 1629065, 203922], "2ptm": 0, "3ptm": 0, "ftm": 0, "2pta": 0, "3pta": 0, "fta": 0, "poss": 0, "tov": 0, "ast": 0, "foul_s": 0, "foul_reg": 0, "d_reb": 0, "o_reb": 0, "min": 0, "subs": 1}, "[1629673, 202692, 1629016, 1629065, 203922]": {"lineup": [1629673, 202692, 1629016, 1629065, 203922], "2ptm": 0, "3ptm": 0, "ftm": 1, "2pta": 0, "3pta": 0, "fta": 1, "poss": 0, "tov": 0, "ast": 0, "foul_s": 0, "foul_reg": 0, "d_reb": 0, "o_reb": 0, "min": 27, "subs": 1}, "[1629673, 1627737, 1629016, 1629065, 203922]": {"lineup": [1629673, 1627737, 1629016, 1629065, 203922], "2ptm": 0, "3ptm": 1, "ftm": 0, "2pta": 0, "3pta": 1, "fta": 0, "poss": 1, "tov": 0, "ast": 1, "foul_s": 1, "foul_reg": 0, "d_reb": 0, "o_reb": 0, "min": 45, "subs": 0}}}}