{"GAME_ID":{"0":"0021900611","1":"0021900611","2":"0021900611","3":"0021900611","4":"0021900611","5":"0021900611","6":"0021900611","7":"0021900611","8":"0021900611","9":"0021900611","10":"0021900611","11":"0021900611","12":"0021900611","13":"0021900611","14":"0021900611","15":"0021900611","16":"0021900611","17":"0021900611","18":"0021900611","19":"0021900611","20":"0021900611","21":"0021900611","22":"0021900611","23":"0021900611"},"TEAM_ID":{"0":1610612757,"1":1610612757,"2":1610612757,"3":1610612757,"4":1610612757,"5":1610612757,"6":1610612757,"7":1610612757,"8":1610612757,"9":1610612757,"10":1610612757,"11":1610612757,"12":1610612745,"13":1610612745,"14":1610612745,"15":1610612745,"16":1610612745,"17":1610612745,"18":1610612745,"19":1610612745,"20":1610612745,"21":1610612745,"22":1610612745,"23":1610612745},"TEAM_ABBREVIATION":{"0":"POR","1":"POR","2":"POR","3":"POR","4":"POR","5":"POR","6":"POR","7":"POR","8":"POR","9":"POR","10":"POR","11":"POR","12":"HOU","13":"HOU","14":"HOU","15":"HOU","16":"HOU","17":"HOU","18":"HOU","19":"HOU","20":"HOU","21":"HOU","22":"HOU","23":"HOU"},"TEAM_CITY":{"0":"Portland","1":"Portland","2":"Portland","3":"Portland","4":"Portland","5":"Portland","6":"Portland","7":"Portland","8":"Portland","9":"Portland","10":"Portland","11":"Portland","12":"Houston","13":"Houston","14":"Houston","15":"Houston","16":"Houston","17":"Houston","18":"Houston","19":"Houston","20":"Houston","21":"Houston","22":"Houston","23":"Houston"},"PLAYER_ID":{"0":203145,"1":2546,"2":202355,"3":203468,"4":203081,"5":1629642,"6":1629014,"7":1629018,"8":201229,"9":1626209,"10":1629658,"11":203994,"12":203463,"13":200782,"14":203991,"15":201935,"16":201566,"17":1627863,"18":201569,"19":203085,"20":1628392,"21":2199,"22":1629598,"23":200757},"PLAYER_NAME":{"0":"Kent Bazemore","1":"Carmelo Anthony","2":"Hassan Whiteside","3":"CJ McCollum","4":"Damian Lillard","5":"Nassir Little","6":"Anfernee Simons","7":"Gary Trent Jr.","8":"Anthony Tolliver","9":"Mario Hezonja","10":"Jaylen Hoard","11":"Jusuf Nurkic","12":"Ben McLemore","13":"P.J. Tucker","14":"Clint Capela","15":"James Harden","16":"Russell Westbrook","17":"Danuel House Jr.","18":"Eric Gordon","19":"Austin Rivers","20":"Isaiah Hartenstein","21":"Tyson Chandler","22":"Chris Clemons","23":"Thabo Sefolosha"},"START_POSITION":{"0":"F","1":"F","2":"C","3":"G","4":"G","5":"","6":"","7":"","8":"","9":"","10":"","11":"","12":"F","13":"F","14":"C","15":"G","16":"G","17":"","18":"","19":"","20":"","21":"","22":"","23":""},"COMMENT":{"0":"","1":"","2":"","3":"","4":"","5":"","6":"","7":"","8":"","9":"DND - Injury\/Illness                    ","10":"DNP - Coach's Decision                  ","11":"DND - Injury\/Illness                    ","12":"","13":"","14":"","15":"","16":"","17":"","18":"","19":"","20":"","21":"DNP - Coach's Decision                  ","22":"DNP - Coach's Decision                  ","23":"DNP - Coach's Decision                  "},"MIN":{"0":"32:13","1":"33:58","2":"37:00","3":"38:04","4":"37:48","5":"12:35","6":"20:35","7":"15:20","8":"12:27","9":null,"10":null,"11":null,"12":"23:36","13":"30:05","14":"36:04","15":"36:24","16":"41:59","17":"22:05","18":"30:40","19":"18:11","20":"0:56","21":null,"22":null,"23":null},"FGM":{"0":3.0,"1":7.0,"2":7.0,"3":9.0,"4":8.0,"5":1.0,"6":1.0,"7":2.0,"8":3.0,"9":null,"10":null,"11":null,"12":6.0,"13":1.0,"14":7.0,"15":3.0,"16":11.0,"17":2.0,"18":7.0,"19":1.0,"20":0.0,"21":null,"22":null,"23":null},"FGA":{"0":13.0,"1":10.0,"2":16.0,"3":18.0,"4":20.0,"5":2.0,"6":5.0,"7":4.0,"8":7.0,"9":null,"10":null,"11":null,"12":15.0,"13":3.0,"14":14.0,"15":12.0,"16":22.0,"17":7.0,"18":18.0,"19":5.0,"20":0.0,"21":null,"22":null,"23":null},"FG_PCT":{"0":0.231,"1":0.7,"2":0.438,"3":0.5,"4":0.4,"5":0.5,"6":0.2,"7":0.5,"8":0.429,"9":null,"10":null,"11":null,"12":0.4,"13":0.333,"14":0.5,"15":0.25,"16":0.5,"17":0.286,"18":0.389,"19":0.2,"20":0.0,"21":null,"22":null,"23":null},"FG3M":{"0":2.0,"1":1.0,"2":0.0,"3":3.0,"4":1.0,"5":1.0,"6":0.0,"7":1.0,"8":2.0,"9":null,"10":null,"11":null,"12":5.0,"13":1.0,"14":0.0,"15":1.0,"16":2.0,"17":1.0,"18":6.0,"19":0.0,"20":0.0,"21":null,"22":null,"23":null},"FG3A":{"0":10.0,"1":2.0,"2":0.0,"3":6.0,"4":8.0,"5":1.0,"6":1.0,"7":3.0,"8":5.0,"9":null,"10":null,"11":null,"12":13.0,"13":3.0,"14":0.0,"15":6.0,"16":5.0,"17":6.0,"18":13.0,"19":3.0,"20":0.0,"21":null,"22":null,"23":null},"FG3_PCT":{"0":0.2,"1":0.5,"2":0.0,"3":0.5,"4":0.125,"5":1.0,"6":0.0,"7":0.333,"8":0.4,"9":null,"10":null,"11":null,"12":0.385,"13":0.333,"14":0.0,"15":0.167,"16":0.4,"17":0.167,"18":0.462,"19":0.0,"20":0.0,"21":null,"22":null,"23":null},"FTM":{"0":4.0,"1":3.0,"2":4.0,"3":3.0,"4":8.0,"5":2.0,"6":0.0,"7":0.0,"8":0.0,"9":null,"10":null,"11":null,"12":0.0,"13":0.0,"14":0.0,"15":6.0,"16":7.0,"17":2.0,"18":0.0,"19":0.0,"20":0.0,"21":null,"22":null,"23":null},"FTA":{"0":4.0,"1":3.0,"2":8.0,"3":4.0,"4":8.0,"5":2.0,"6":0.0,"7":0.0,"8":0.0,"9":null,"10":null,"11":null,"12":0.0,"13":0.0,"14":0.0,"15":8.0,"16":12.0,"17":2.0,"18":0.0,"19":1.0,"20":0.0,"21":null,"22":null,"23":null},"FT_PCT":{"0":1.0,"1":1.0,"2":0.5,"3":0.75,"4":1.0,"5":1.0,"6":0.0,"7":0.0,"8":0.0,"9":null,"10":null,"11":null,"12":0.0,"13":0.0,"14":0.0,"15":0.75,"16":0.583,"17":1.0,"18":0.0,"19":0.0,"20":0.0,"21":null,"22":null,"23":null},"OREB":{"0":1.0,"1":1.0,"2":7.0,"3":0.0,"4":1.0,"5":1.0,"6":0.0,"7":0.0,"8":1.0,"9":null,"10":null,"11":null,"12":0.0,"13":1.0,"14":7.0,"15":3.0,"16":1.0,"17":0.0,"18":0.0,"19":0.0,"20":0.0,"21":null,"22":null,"23":null},"DREB":{"0":8.0,"1":11.0,"2":11.0,"3":1.0,"4":6.0,"5":1.0,"6":4.0,"7":2.0,"8":2.0,"9":null,"10":null,"11":null,"12":2.0,"13":3.0,"14":11.0,"15":5.0,"16":10.0,"17":2.0,"18":2.0,"19":3.0,"20":0.0,"21":null,"22":null,"23":null},"REB":{"0":9.0,"1":12.0,"2":18.0,"3":1.0,"4":7.0,"5":2.0,"6":4.0,"7":2.0,"8":3.0,"9":null,"10":null,"11":null,"12":2.0,"13":4.0,"14":18.0,"15":8.0,"16":11.0,"17":2.0,"18":2.0,"19":3.0,"20":0.0,"21":null,"22":null,"23":null},"AST":{"0":3.0,"1":1.0,"2":0.0,"3":6.0,"4":7.0,"5":0.0,"6":4.0,"7":1.0,"8":0.0,"9":null,"10":null,"11":null,"12":0.0,"13":1.0,"14":2.0,"15":7.0,"16":12.0,"17":1.0,"18":1.0,"19":0.0,"20":0.0,"21":null,"22":null,"23":null},"STL":{"0":1.0,"1":0.0,"2":0.0,"3":2.0,"4":2.0,"5":0.0,"6":1.0,"7":0.0,"8":0.0,"9":null,"10":null,"11":null,"12":1.0,"13":1.0,"14":1.0,"15":0.0,"16":1.0,"17":0.0,"18":0.0,"19":0.0,"20":0.0,"21":null,"22":null,"23":null},"BLK":{"0":1.0,"1":0.0,"2":2.0,"3":1.0,"4":0.0,"5":0.0,"6":0.0,"7":0.0,"8":0.0,"9":null,"10":null,"11":null,"12":1.0,"13":0.0,"14":1.0,"15":2.0,"16":0.0,"17":0.0,"18":0.0,"19":0.0,"20":0.0,"21":null,"22":null,"23":null},"TO":{"0":1.0,"1":1.0,"2":1.0,"3":2.0,"4":1.0,"5":0.0,"6":0.0,"7":1.0,"8":0.0,"9":null,"10":null,"11":null,"12":1.0,"13":3.0,"14":3.0,"15":2.0,"16":1.0,"17":1.0,"18":0.0,"19":1.0,"20":0.0,"21":null,"22":null,"23":null},"PF":{"0":2.0,"1":1.0,"2":4.0,"3":3.0,"4":3.0,"5":2.0,"6":1.0,"7":2.0,"8":1.0,"9":null,"10":null,"11":null,"12":2.0,"13":5.0,"14":2.0,"15":5.0,"16":1.0,"17":4.0,"18":2.0,"19":0.0,"20":1.0,"21":null,"22":null,"23":null},"PTS":{"0":12.0,"1":18.0,"2":18.0,"3":24.0,"4":25.0,"5":5.0,"6":2.0,"7":5.0,"8":8.0,"9":null,"10":null,"11":null,"12":17.0,"13":3.0,"14":14.0,"15":13.0,"16":31.0,"17":7.0,"18":20.0,"19":2.0,"20":0.0,"21":null,"22":null,"23":null},"PLUS_MINUS":{"0":14.0,"1":4.0,"2":7.0,"3":11.0,"4":4.0,"5":8.0,"6":4.0,"7":-3.0,"8":1.0,"9":null,"10":null,"11":null,"12":-4.0,"13":-7.0,"14":-2.0,"15":-11.0,"16":1.0,"17":-3.0,"18":-11.0,"19":-8.0,"20":-5.0,"21":null,"22":null,"23":null}}