{"GAME_ID":{"0":"0021900545","1":"0021900545","2":"0021900545","3":"0021900545","4":"0021900545","5":"0021900545","6":"0021900545","7":"0021900545","8":"0021900545","9":"0021900545","10":"0021900545","11":"0021900545","12":"0021900545","13":"0021900545","14":"0021900545","15":"0021900545","16":"0021900545","17":"0021900545","18":"0021900545","19":"0021900545"},"TEAM_ID":{"0":1610612741,"1":1610612741,"2":1610612741,"3":1610612741,"4":1610612741,"5":1610612741,"6":1610612741,"7":1610612741,"8":1610612741,"9":1610612741,"10":1610612742,"11":1610612742,"12":1610612742,"13":1610612742,"14":1610612742,"15":1610612742,"16":1610612742,"17":1610612742,"18":1610612742,"19":1610612742},"TEAM_ABBREVIATION":{"0":"CHI","1":"CHI","2":"CHI","3":"CHI","4":"CHI","5":"CHI","6":"CHI","7":"CHI","8":"CHI","9":"CHI","10":"DAL","11":"DAL","12":"DAL","13":"DAL","14":"DAL","15":"DAL","16":"DAL","17":"DAL","18":"DAL","19":"DAL"},"TEAM_CITY":{"0":"Chicago","1":"Chicago","2":"Chicago","3":"Chicago","4":"Chicago","5":"Chicago","6":"Chicago","7":"Chicago","8":"Chicago","9":"Chicago","10":"Dallas","11":"Dallas","12":"Dallas","13":"Dallas","14":"Dallas","15":"Dallas","16":"Dallas","17":"Dallas","18":"Dallas","19":"Dallas"},"TEAM_NICKNAME":{"0":"Bulls","1":"Bulls","2":"Bulls","3":"Bulls","4":"Bulls","5":"Bulls","6":"Bulls","7":"Bulls","8":"Bulls","9":"Bulls","10":"Mavericks","11":"Mavericks","12":"Mavericks","13":"Mavericks","14":"Mavericks","15":"Mavericks","16":"Mavericks","17":"Mavericks","18":"Mavericks","19":"Mavericks"},"PLAYER_ID":{"0":1627739,"1":1628374,"2":1628976,"3":203897,"4":203107,"5":1629632,"6":1629655,"7":201152,"8":1628990,"9":1627885,"10":203501,"11":1627827,"12":203939,"13":200826,"14":1629029,"15":203552,"16":1628467,"17":1626153,"18":1628973,"19":1628382},"PLAYER_NAME":{"0":"Kris Dunn","1":"Lauri Markkanen","2":"Wendell Carter Jr.","3":"Zach LaVine","4":"Tomas Satoransky","5":"Coby White","6":"Daniel Gafford","7":"Thaddeus Young","8":"Chandler Hutchison","9":"Shaquille Harrison","10":"Tim Hardaway Jr.","11":"Dorian Finney-Smith","12":"Dwight Powell","13":"J.J. Barea","14":"Luka Doncic","15":"Seth Curry","16":"Maxi Kleber","17":"Delon Wright","18":"Jalen Brunson","19":"Justin Jackson"},"START_POSITION":{"0":"F","1":"F","2":"C","3":"G","4":"G","5":"","6":"","7":"","8":"","9":"","10":"F","11":"F","12":"C","13":"G","14":"G","15":"","16":"","17":"","18":"","19":""},"COMMENT":{"0":"","1":"","2":"","3":"","4":"","5":"","6":"","7":"","8":"","9":"","10":"","11":"","12":"","13":"","14":"","15":"","16":"","17":"","18":"","19":""},"MATCHUP_MIN":{"0":"7:35","1":"11:42","2":"5:44","3":"12:59","4":"11:43","5":"7:35","6":"8:50","7":"9:40","8":"2:03","9":"3:28","10":"7:57","11":"12:52","12":"10:49","13":"5:42","14":"12:01","15":"7:04","16":"8:31","17":"7:43","18":"4:37","19":"5:07"},"PARTIAL_POSS":{"0":28.53,"1":44.52,"2":23.01,"3":48.82,"4":43.3,"5":27.8,"6":31.02,"7":35.85,"8":8.61,"9":13.55,"10":29.72,"11":50.87,"12":40.19,"13":19.72,"14":47.55,"15":25.75,"16":36.08,"17":31.81,"18":17.21,"19":19.9},"SWITCHES_ON":{"0":0,"1":0,"2":0,"3":0,"4":0,"5":0,"6":0,"7":0,"8":0,"9":0,"10":0,"11":0,"12":0,"13":0,"14":0,"15":0,"16":0,"17":0,"18":0,"19":0},"PLAYER_PTS":{"0":12,"1":13,"2":4,"3":12,"4":16,"5":18,"6":14,"7":13,"8":0,"9":11,"10":11,"11":16,"12":19,"13":2,"14":8,"15":2,"16":21,"17":9,"18":9,"19":6},"DREB":{"0":1,"1":7,"2":3,"3":4,"4":2,"5":0,"6":5,"7":6,"8":0,"9":0,"10":3,"11":3,"12":4,"13":1,"14":10,"15":1,"16":2,"17":4,"18":2,"19":2},"MATCHUP_AST":{"0":9,"1":3,"2":0,"3":5,"4":3,"5":2,"6":0,"7":1,"8":0,"9":1,"10":1,"11":5,"12":3,"13":1,"14":4,"15":0,"16":1,"17":2,"18":3,"19":2},"MATCHUP_TOV":{"0":1,"1":1,"2":1,"3":0,"4":4,"5":2,"6":0,"7":2,"8":0,"9":2,"10":0,"11":1,"12":1,"13":1,"14":1,"15":1,"16":0,"17":1,"18":1,"19":1},"STL":{"0":1,"1":1,"2":1,"3":3,"4":1,"5":0,"6":0,"7":3,"8":0,"9":0,"10":1,"11":1,"12":0,"13":1,"14":0,"15":0,"16":1,"17":0,"18":1,"19":0},"BLK":{"0":0,"1":0,"2":1,"3":2,"4":0,"5":0,"6":2,"7":1,"8":0,"9":1,"10":0,"11":0,"12":0,"13":0,"14":1,"15":1,"16":1,"17":2,"18":1,"19":0},"MATCHUP_FGM":{"0":4,"1":5,"2":1,"3":5,"4":5,"5":7,"6":6,"7":6,"8":0,"9":4,"10":4,"11":7,"12":7,"13":1,"14":4,"15":1,"16":8,"17":4,"18":4,"19":3},"MATCHUP_FGA":{"0":6,"1":8,"2":5,"3":12,"4":9,"5":11,"6":10,"7":13,"8":1,"9":6,"10":5,"11":17,"12":13,"13":2,"14":15,"15":4,"16":15,"17":10,"18":7,"19":4},"MATCHUP_FG_PCT":{"0":0.667,"1":0.625,"2":0.2,"3":0.417,"4":0.556,"5":0.636,"6":0.6,"7":0.462,"8":0.0,"9":0.667,"10":0.8,"11":0.412,"12":0.538,"13":0.5,"14":0.267,"15":0.25,"16":0.533,"17":0.4,"18":0.571,"19":0.75},"MATCHUP_FG3M":{"0":1,"1":1,"2":0,"3":2,"4":3,"5":2,"6":1,"7":1,"8":0,"9":3,"10":3,"11":1,"12":1,"13":0,"14":0,"15":0,"16":1,"17":1,"18":1,"19":0},"MATCHUP_FG3A":{"0":3,"1":3,"2":2,"3":6,"4":4,"5":6,"6":4,"7":5,"8":1,"9":4,"10":3,"11":6,"12":1,"13":0,"14":6,"15":2,"16":4,"17":3,"18":2,"19":0},"MATCHUP_FG3_PCT":{"0":0.333,"1":0.333,"2":0.0,"3":0.333,"4":0.75,"5":0.333,"6":0.25,"7":0.2,"8":0.0,"9":0.75,"10":1.0,"11":0.167,"12":1.0,"13":0.0,"14":0.0,"15":0.0,"16":0.25,"17":0.333,"18":0.5,"19":0.0}}